odoo10_addon_l10n_es_aeat_mod349-10.0.2.2.6-nspkg.pth
odoo/addons/l10n_es_aeat_mod349/README.rst
odoo/addons/l10n_es_aeat_mod349/__init__.py
odoo/addons/l10n_es_aeat_mod349/__manifest__.py
odoo/addons/l10n_es_aeat_mod349/hooks.py
odoo/addons/l10n_es_aeat_mod349/data/aeat_349_map_data.xml
odoo/addons/l10n_es_aeat_mod349/data/aeat_export_mod349_data.xml
odoo/addons/l10n_es_aeat_mod349/data/aeat_export_mod349_partner_data.xml
odoo/addons/l10n_es_aeat_mod349/data/aeat_export_mod349_partner_refund_data.xml
odoo/addons/l10n_es_aeat_mod349/docs/BOE-A-2010-5098.pdf
odoo/addons/l10n_es_aeat_mod349/docs/NREG-349-2016.docx
odoo/addons/l10n_es_aeat_mod349/i18n/bg.po
odoo/addons/l10n_es_aeat_mod349/i18n/ca.po
odoo/addons/l10n_es_aeat_mod349/i18n/cs.po
odoo/addons/l10n_es_aeat_mod349/i18n/de.po
odoo/addons/l10n_es_aeat_mod349/i18n/es.po
odoo/addons/l10n_es_aeat_mod349/i18n/es_CO.po
odoo/addons/l10n_es_aeat_mod349/i18n/es_CR.po
odoo/addons/l10n_es_aeat_mod349/i18n/es_ES.po
odoo/addons/l10n_es_aeat_mod349/i18n/eu.po
odoo/addons/l10n_es_aeat_mod349/i18n/fr.po
odoo/addons/l10n_es_aeat_mod349/i18n/gl.po
odoo/addons/l10n_es_aeat_mod349/i18n/hr.po
odoo/addons/l10n_es_aeat_mod349/i18n/l10n_es_aeat_mod349.pot
odoo/addons/l10n_es_aeat_mod349/i18n/nl.po
odoo/addons/l10n_es_aeat_mod349/i18n/pl.po
odoo/addons/l10n_es_aeat_mod349/i18n/pt.po
odoo/addons/l10n_es_aeat_mod349/i18n/pt_BR.po
odoo/addons/l10n_es_aeat_mod349/i18n/ru.po
odoo/addons/l10n_es_aeat_mod349/i18n/sl.po
odoo/addons/l10n_es_aeat_mod349/i18n/sv.po
odoo/addons/l10n_es_aeat_mod349/i18n/tr.po
odoo/addons/l10n_es_aeat_mod349/i18n/vi.po
odoo/addons/l10n_es_aeat_mod349/migrations/10.0.2.1.0/post-migration.py
odoo/addons/l10n_es_aeat_mod349/migrations/10.0.2.1.0/pre-migration.py
odoo/addons/l10n_es_aeat_mod349/models/__init__.py
odoo/addons/l10n_es_aeat_mod349/models/account_invoice.py
odoo/addons/l10n_es_aeat_mod349/models/account_move_line.py
odoo/addons/l10n_es_aeat_mod349/models/account_tax.py
odoo10_addon_l10n_es_aeat_mod349-10.0.2.2.6.dist-info/METADATA
odoo10_addon_l10n_es_aeat_mod349-10.0.2.2.6.dist-info/WHEEL
odoo10_addon_l10n_es_aeat_mod349-10.0.2.2.6.dist-info/namespace_packages.txt
odoo10_addon_l10n_es_aeat_mod349-10.0.2.2.6.dist-info/top_level.txt
odoo10_addon_l10n_es_aeat_mod349-10.0.2.2.6.dist-info/RECORD
