Metadata-Version: 2.1
Name: odoo10-addon-l10n-es-aeat-mod349
Version: 10.0.2.2.6
Summary: Modelo 349 AEAT
Home-page: https://github.com/OCA/l10n-spain
Author: Pexego, Top Consultant, Tecnativa, Eficent, Odoo Community Association (OCA)
Author-email: support@odoo-community.org
License: AGPL-3
Platform: UNKNOWN
Classifier: Programming Language :: Python
Classifier: Framework :: Odoo
Classifier: License :: OSI Approved :: GNU Affero General Public License v3
Requires-Python: ~=2.7
Requires-Dist: odoo10-addon-l10n-es-aeat
Requires-Dist: odoo (<10.1dev,>=10.0)
